Workbook

Sheet Report
A1: Sales Report - Nour Fashion (Jun - Aug 2026)
A2: Built from the cleaned sales file. Every number below is a formula that reads the 'Cleaned Data' sheet. Revenue = Qty x Price (gross, includes cancelled/returned orders).
A4: Key numbers
A5: Metric | B5: Value
A6: Total orders | B6: =COUNTA('Cleaned Data'!$A$2:$A$451) -> 450
A7: Total revenue (EGP) | B7: =SUM('Cleaned Data'!$M$2:$M$451) -> 364210
A8: Cancelled + returned orders | B8: =COUNTIF('Cleaned Data'!$K$2:$K$451,"Cancelled")+COUNTIF('Cleaned Data'!$K$2:$K$451,"Returned") -> 136
A9: Cancelled + returned share | B9: =B8/B6 -> 0.30222222
A11: Top 5 products by revenue
A12: Ranked by revenue (not units): units are nearly flat across products, so price is what separates them.
A13: Rank | B13: Product | C13: Revenue (EGP) | D13: Units sold | E13: Orders
A14: 1 | B14: Jacket | C14: =SUMIFS('Cleaned Data'!$M$2:$M$451,'Cleaned Data'!$F$2:$F$451,B14) -> 66000 | D14: =SUMIFS('Cleaned Data'!$H$2:$H$451,'Cleaned Data'!$F$2:$F$451,B14) -> 66 | E14: =COUNTIFS('Cleaned Data'!$F$2:$F$451,B14) -> 46
A15: 2 | B15: Abaya | C15: =SUMIFS('Cleaned Data'!$M$2:$M$451,'Cleaned Data'!$F$2:$F$451,B15) -> 63000 | D15: =SUMIFS('Cleaned Data'!$H$2:$H$451,'Cleaned Data'!$F$2:$F$451,B15) -> 73 | E15: =COUNTIFS('Cleaned Data'!$F$2:$F$451,B15) -> 47
A16: 3 | B16: Sneakers | C16: =SUMIFS('Cleaned Data'!$M$2:$M$451,'Cleaned Data'!$F$2:$F$451,B16) -> 56050 | D16: =SUMIFS('Cleaned Data'!$H$2:$H$451,'Cleaned Data'!$F$2:$F$451,B16) -> 59 | E16: =COUNTIFS('Cleaned Data'!$F$2:$F$451,B16) -> 43
A17: 4 | B17: Dress | C17: =SUMIFS('Cleaned Data'!$M$2:$M$451,'Cleaned Data'!$F$2:$F$451,B17) -> 52500 | D17: =SUMIFS('Cleaned Data'!$H$2:$H$451,'Cleaned Data'!$F$2:$F$451,B17) -> 76 | E17: =COUNTIFS('Cleaned Data'!$F$2:$F$451,B17) -> 52
A18: 5 | B18: Jeans | C18: =SUMIFS('Cleaned Data'!$M$2:$M$451,'Cleaned Data'!$F$2:$F$451,B18) -> 36300 | D18: =SUMIFS('Cleaned Data'!$H$2:$H$451,'Cleaned Data'!$F$2:$F$451,B18) -> 69 | E18: =COUNTIFS('Cleaned Data'!$F$2:$F$451,B18) -> 44
A20: Orders by city
A21: Orders with an unknown city are left out of this table (see Cleaning Notes).
A22: City | B22: Orders | C22: Revenue (EGP)
A23: Cairo | B23: =COUNTIFS('Cleaned Data'!$E$2:$E$451,A23) -> 118 | C23: =SUMIFS('Cleaned Data'!$M$2:$M$451,'Cleaned Data'!$E$2:$E$451,A23) -> 95090
A24: Alexandria | B24: =COUNTIFS('Cleaned Data'!$E$2:$E$451,A24) -> 88 | C24: =SUMIFS('Cleaned Data'!$M$2:$M$451,'Cleaned Data'!$E$2:$E$451,A24) -> 68950
A25: Giza | B25: =COUNTIFS('Cleaned Data'!$E$2:$E$451,A25) -> 88 | C25: =SUMIFS('Cleaned Data'!$M$2:$M$451,'Cleaned Data'!$E$2:$E$451,A25) -> 69280
A26: Sohag | B26: =COUNTIFS('Cleaned Data'!$E$2:$E$451,A26) -> 41 | C26: =SUMIFS('Cleaned Data'!$M$2:$M$451,'Cleaned Data'!$E$2:$E$451,A26) -> 34530
A27: Mansoura | B27: =COUNTIFS('Cleaned Data'!$E$2:$E$451,A27) -> 37 | C27: =SUMIFS('Cleaned Data'!$M$2:$M$451,'Cleaned Data'!$E$2:$E$451,A27) -> 25970
A28: Assiut | B28: =COUNTIFS('Cleaned Data'!$E$2:$E$451,A28) -> 34 | C28: =SUMIFS('Cleaned Data'!$M$2:$M$451,'Cleaned Data'!$E$2:$E$451,A28) -> 34760
A29: Tanta | B29: =COUNTIFS('Cleaned Data'!$E$2:$E$451,A29) -> 24 | C29: =SUMIFS('Cleaned Data'!$M$2:$M$451,'Cleaned Data'!$E$2:$E$451,A29) -> 18690
A30: Top city (by orders) | B30: =INDEX(A23:A29,MATCH(MAX(B23:B29),B23:B29,0)) -> Cairo | C30: =MAX(B23:B29) -> 118
A33: Monthly sales
A34: Month | B34: Orders | C34: Revenue (EGP) | D34: Units sold
A35: 2026-06 | B35: =COUNTIFS('Cleaned Data'!$L$2:$L$451,A35) -> 119 | C35: =SUMIFS('Cleaned Data'!$M$2:$M$451,'Cleaned Data'!$L$2:$L$451,A35) -> 95100 | D35: =SUMIFS('Cleaned Data'!$H$2:$H$451,'Cleaned Data'!$L$2:$L$451,A35) -> 180
A36: 2026-07 | B36: =COUNTIFS('Cleaned Data'!$L$2:$L$451,A36) -> 167 | C36: =SUMIFS('Cleaned Data'!$M$2:$M$451,'Cleaned Data'!$L$2:$L$451,A36) -> 133960 | D36: =SUMIFS('Cleaned Data'!$H$2:$H$451,'Cleaned Data'!$L$2:$L$451,A36) -> 250
A37: 2026-08 | B37: =COUNTIFS('Cleaned Data'!$L$2:$L$451,A37) -> 164 | C37: =SUMIFS('Cleaned Data'!$M$2:$M$451,'Cleaned Data'!$L$2:$L$451,A37) -> 135150 | D37: =SUMIFS('Cleaned Data'!$H$2:$H$451,'Cleaned Data'!$L$2:$L$451,A37) -> 246

Sheet Cleaned Data
A1: Order ID | B1: Order Date | C1: Customer Name | D1: Phone | E1: City | F1: Product | G1: Category | H1: Qty | I1: Price | J1: Payment Method | K1: Status | L1: Month | M1: Revenue
A2: 1032 | B2: 46199 | C2: Ali Mahmoud | D2: 01169801375 | E2: Cairo | F2: Scarf | G2: Accessories | H2: 2 | I2: 120 | J2: Vodafone Cash | K2: Cancelled | L2: 2026-06 | M2: =IF(AND(ISNUMBER(H2),ISNUMBER(I2)),H2*I2,"") -> 240
A3: 1222 | B3: 46238 | C3: آية خليل | D3: 01573841107 | E3: Sohag | F3: Hoodie | G3: Tops | H3: 1 | I3: 450 | J3: Credit Card | K3: Delivered | L3: 2026-08 | M3: =IF(AND(ISNUMBER(H3),ISNUMBER(I3)),H3*I3,"") -> 450
A4: 1301 | B4: 46204 | C4: منى صلاح | D4: 01299957026 | E4: Alexandria | F4: Hoodie | G4: Tops | H4: 1 | I4: 450 | J4: Credit Card | K4: Delivered | L4: 2026-07 | M4: =IF(AND(ISNUMBER(H4),ISNUMBER(I4)),H4*I4,"") -> 450
A5: 1270 | B5: 46259 | C5: أحمد فتحي | D5: 01214951097 | E5: Giza | F5: Sneakers | G5: Shoes | H5: 2 | I5: 950 | J5: Cash On Delivery | K5: Delivered | L5: 2026-08 | M5: =IF(AND(ISNUMBER(H5),ISNUMBER(I5)),H5*I5,"") -> 1900
A6: 1001 | B6: 46177 | C6: Sara Hassan | D6: 01150165258 | F6: Scarf | G6: Accessories | H6: 1 | I6: 120 | J6: Credit Card | K6: Delivered | L6: 2026-06 | M6: =IF(AND(ISNUMBER(H6),ISNUMBER(I6)),H6*I6,"") -> 120
A7: 1387 | B7: 46225 | C7: عمر السيد | D7: Not provided | E7: Alexandria | F7: Sneakers | G7: Shoes | H7: 1 | I7: 950 | J7: Vodafone Cash | K7: Cancelled | L7: 2026-07 | M7: =IF(AND(ISNUMBER(H7),ISNUMBER(I7)),H7*I7,"") -> 950
A8: 1446 | B8: 46192 | C8: هدى عادل | D8: 01027937196 | E8: Cairo | F8: Jeans | G8: Bottoms | H8: 2 | I8: 550 | J8: Instapay | K8: Delivered | L8: 2026-06 | M8: =IF(AND(ISNUMBER(H8),ISNUMBER(I8)),H8*I8,"") -> 1100
A9: 1383 | B9: 46243 | C9: ياسمين حسن | D9: 01020992514 | E9: Cairo | F9: Sneakers | G9: Shoes | H9: 1 | I9: 950 | J9: Credit Card | K9: Returned | L9: 2026-08 | M9: =IF(AND(ISNUMBER(H9),ISNUMBER(I9)),H9*I9,"") -> 950
A10: 1425 | B10: 46257 | C10: رنا عادل | D10: 01517656586 | E10: Mansoura | F10: Hoodie | G10: Tops | H10: 1 | I10: 450 | J10: Instapay | K10: Returned | L10: 2026-08 | M10: =IF(AND(ISNUMBER(H10),ISNUMBER(I10)),H10*I10,"") -> 450
A11: 1217 | B11: 46192 | C11: منى صلاح | D11: 01039520262 | E11: Alexandria | F11: Sneakers | G11: Shoes | H11: 1 | I11: 950 | J11: Cash On Delivery | K11: Delivered | L11: 2026-06 | M11: =IF(AND(ISNUMBER(H11),ISNUMBER(I11)),H11*I11,"") -> 950
A12: 1125 | B12: 46213 | C12: أحمد إبراهيم | D12: Not provided | E12: Cairo | F12: Hoodie | G12: Tops | H12: 3 | I12: 450 | J12: Instapay | K12: Shipped | L12: 2026-07 | M12: =IF(AND(ISNUMBER(H12),ISNUMBER(I12)),H12*I12,"") -> 1350
A13: 1336 | B13: 46220 | C13: أحمد فتحي | D13: 01082244010 | E13: Cairo | F13: Sneakers | G13: Shoes | H13: 1 | I13: 950 | J13: Vodafone Cash | K13: Cancelled | L13: 2026-07 | M13: =IF(AND(ISNUMBER(H13),ISNUMBER(I13)),H13*I13,"") -> 950
A14: 1419 | B14: 46233 | C14: نور حسن | D14: 01246940799 | E14: Giza | F14: Jeans | G14: Bottoms | H14: 1 | I14: 550 | J14: Credit Card | K14: Delivered | L14: 2026-07 | M14: =IF(AND(ISNUMBER(H14),ISNUMBER(I14)),H14*I14,"") -> 550
A15: 1319 | B15: 46178 | C15: حسن حسن | D15: 01190676524 | E15: Tanta | F15: Dress | G15: Dresses | H15: 1 | I15: 750 | J15: Vodafone Cash | K15: Cancelled | L15: 2026-06 | M15: =IF(AND(ISNUMBER(H15),ISNUMBER(I15)),H15*I15,"") -> 750
A16: 1399 | B16: 46238 | C16: فاطمة رمضان | D16: 01156105767 | E16: Giza | F16: Dress | G16: Dresses | H16: 1 | I16: 750 | J16: Instapay | K16: Delivered | L16: 2026-08 | M16: =IF(AND(ISNUMBER(H16),ISNUMBER(I16)),H16*I16,"") -> 750
A17: 1051 | B17: 46219 | C17: سارة السيد | D17: 01114835122 | E17: Sohag | F17: Skirt | G17: Bottoms | H17: 2 | I17: 300 | J17: Instapay | K17: Delivered | L17: 2026-07 | M17: =IF(AND(ISNUMBER(H17),ISNUMBER(I17)),H17*I17,"") -> 600
A18: 1206 | B18: 46263 | C18: Esraa Ibrahim | D18: 01153485815 | E18: Giza | F18: Sneakers | G18: Shoes | H18: 1 | I18: 950 | J18: Instapay | K18: Delivered | L18: 2026-08 | M18: =IF(AND(ISNUMBER(H18),ISNUMBER(I18)),H18*I18,"") -> 950
... A33: 1078 | B33: 46240 | C33: يوسف يوسف | D33: 01136197238 | E33: Cairo | F33: Abaya | G33: Dresses | H33: 2 | I33: 900 | J33: Vodafone Cash | K33: Delivered | L33: 2026-08 | M33: =IF(AND(ISNUMBER(H33),ISNUMBER(I33)),H33*I33,"") -> 1800
A34: 1201 | B34: 46240 | C34: Yasmine Mahmoud | D34: 01227848126 | F34: Dress | G34: Dresses | H34: 2 | J34: Instapay | K34: Delivered | L34: 2026-08 | M34: =IF(AND(ISNUMBER(H34),ISNUMBER(I34)),H34*I34,"")
A35: 1082 | B35: 46242 | C35: Ahmed Saad | D35: 01216526560 | E35: Giza | F35: Jacket | G35: Outerwear | H35: 1 | I35: 1100 | J35: Cash On Delivery | K35: Cancelled | L35: 2026-08 | M35: =IF(AND(ISNUMBER(H35),ISNUMBER(I35)),H35*I35,"") -> 1100
A36: 1264 | B36: 46264 | C36: رنا محمود | D36: 01094171867 | E36: Alexandria | F36: T-Shirt | G36: Tops | H36: 1 | I36: 180 | J36: Credit Card | K36: Cancelled | L36: 2026-08 | M36: =IF(AND(ISNUMBER(H36),ISNUMBER(I36)),H36*I36,"") -> 180
A37: 1203 | B37: 46189 | C37: هدى السيد | D37: 01139291706 | E37: Cairo | F37: Dress | G37: Dresses | H37: 2 | I37: 750 | J37: Vodafone Cash | K37: Delivered | L37: 2026-06 | M37: =IF(AND(ISNUMBER(H37),ISNUMBER(I37)),H37*I37,"") -> 1500
A38: 1375 | B38: 46222 | C38: Mariam Hassan | D38: 01035134779 | E38: Cairo | F38: Blouse | G38: Tops | H38: 3 | I38: 320 | J38: Vodafone Cash | K38: Delivered | L38: 2026-07 | M38: =IF(AND(ISNUMBER(H38),ISNUMBER(I38)),H38*I38,"") -> 960
A39: 1162 | B39: 46216 | C39: منى عادل | D39: 01573406036 | E39: Giza | F39: Jeans | G39: Bottoms | H39: 2 | I39: 550 | J39: Credit Card | K39: Cancelled | L39: 2026-07 | M39: =IF(AND(ISNUMBER(H39),ISNUMBER(I39)),H39*I39,"") -> 1100
A40: 1288 | B40: 46228 | C40: مريم عبدالله | D40: 01526593358 | E40: Alexandria | F40: Jacket | G40: Outerwear | H40: 2 | I40: 1100 | J40: Credit Card | K40: Delivered | L40: 2026-07 | M40: =IF(AND(ISNUMBER(H40),ISNUMBER(I40)),H40*I40,"") -> 2200
A41: 1044 | B41: 46242 | C41: Ali Mahmoud | D41: 01266589120 | E41: Assiut | F41: Hoodie | G41: Tops | H41: 1 | I41: 450 | J41: Vodafone Cash | K41: Cancelled | L41: 2026-08 | M41: =IF(AND(ISNUMBER(H41),ISNUMBER(I41)),H41*I41,"") -> 450
A42: 1025 | B42: 46222 | C42: Youssef Hassan | D42: 01106617861 | E42: Cairo | F42: Skirt | G42: Bottoms | H42: 1 | I42: 300 | J42: Credit Card | K42: Returned | L42: 2026-07 | M42: =IF(AND(ISNUMBER(H42),ISNUMBER(I42)),H42*I42,"") -> 300
A43: 1049 | B43: 46209 | C43: Sara Mahmoud | D43: 01235254716 | E43: Cairo | F43: Blouse | G43: Tops | H43: 1 | I43: 320 | J43: Vodafone Cash | K43: Delivered | L43: 2026-07 | M43: =IF(AND(ISNUMBER(H43),ISNUMBER(I43)),H43*I43,"") -> 320
A44: 1118 | B44: 46191 | C44: نور رمضان | D44: 01105613279 | E44: Sohag | F44: Hoodie | G44: Tops | H44: 1 | I44: 450 | J44: Vodafone Cash | K44: Delivered | L44: 2026-06 | M44: =IF(AND(ISNUMBER(H44),ISNUMBER(I44)),H44*I44,"") -> 450
A45: 1272 | B45: 46242 | C45: يوسف عادل | D45: 01093465063 | E45: Assiut | F45: Jeans | G45: Bottoms | H45: 1 | I45: 550 | J45: Credit Card | K45: Delivered | L45: 2026-08 | M45: =IF(AND(ISNUMBER(H45),ISNUMBER(I45)),H45*I45,"") -> 550
A46: 1237 | B46: 46185 | C46: فاطمة عبدالله | D46: Not provided | E46: Sohag | F46: Jacket | G46: Outerwear | H46: 1 | I46: 1100 | J46: Cash On Delivery | K46: Cancelled | L46: 2026-06 | M46: =IF(AND(ISNUMBER(H46),ISNUMBER(I46)),H46*I46,"") -> 1100
... A51: 1398 | B51: 46231 | C51: سارة إبراهيم | D51: 01096347511 | E51: Cairo | F51: Jeans | G51: Bottoms | H51: 1 | I51: 550 | J51: Instapay | K51: Delivered | L51: 2026-07 | M51: =IF(AND(ISNUMBER(H51),ISNUMBER(I51)),H51*I51,"") -> 550
A52: 1358 | B52: 46243 | C52: رنا يوسف | D52: 01512314334 | E52: Alexandria | F52: Scarf | G52: Accessories | J52: Credit Card | K52: Delivered | L52: 2026-08 | M52: =IF(AND(ISNUMBER(H52),ISNUMBER(I52)),H52*I52,"")
A53: 1059 | B53: 46258 | C53: Youssef Ibrahim | D53: 01135139635 | E53: Cairo | F53: Dress | G53: Dresses | H53: 1 | I53: 750 | J53: Credit Card | K53: Cancelled | L53: 2026-08 | M53: =IF(AND(ISNUMBER(H53),ISNUMBER(I53)),H53*I53,"") -> 750
A54: 1364 | B54: 46245 | C54: ندى إبراهيم | D54: 01037190873 | E54: Giza | F54: Jacket | G54: Outerwear | H54: 1 | I54: 1100 | J54: Credit Card | K54: Cancelled | L54: 2026-08 | M54: =IF(AND(ISNUMBER(H54),ISNUMBER(I54)),H54*I54,"") -> 1100
A55: 1073 | B55: 46212 | C55: Yasmine Hassan | D55: 01051916768 | E55: Tanta | F55: Hoodie | G55: Tops | H55: 1 | I55: 450 | J55: Cash On Delivery | K55: Delivered | L55: 2026-07 | M55: =IF(AND(ISNUMBER(H55),ISNUMBER(I55)),H55*I55,"") -> 450
A56: 1062 | B56: 46227 | C56: منى فتحي | D56: 01181268518 | F56: Dress | G56: Dresses | H56: 1 | J56: Cash On Delivery | K56: Delivered | L56: 2026-07 | M56: =IF(AND(ISNUMBER(H56),ISNUMBER(I56)),H56*I56,"")
A57: 1094 | B57: 46189 | C57: Dina Ibrahim | D57: 01596732324 | E57: Mansoura | F57: Jeans | G57: Bottoms | H57: 4 | I57: 550 | J57: Credit Card | K57: Returned | L57: 2026-06 | M57: =IF(AND(ISNUMBER(H57),ISNUMBER(I57)),H57*I57,"") -> 2200
A58: 1108 | B58: 46217 | C58: دينا فتحي | D58: 01197553447 | E58: Sohag | F58: Hoodie | G58: Tops | H58: 1 | I58: 450 | J58: Credit Card | K58: Delivered | L58: 2026-07 | M58: =IF(AND(ISNUMBER(H58),ISNUMBER(I58)),H58*I58,"") -> 450
A59: 1337 | B59: 46249 | C59: Rana Hassan | D59: 01282498852 | E59: Giza | F59: T-Shirt | G59: Tops | H59: 2 | I59: 180 | J59: Instapay | K59: Shipped | L59: 2026-08 | M59: =IF(AND(ISNUMBER(H59),ISNUMBER(I59)),H59*I59,"") -> 360
A60: 1002 | B60: 46207 | C60: هدى إبراهيم | D60: 01559358685 | E60: Cairo | F60: Hoodie | G60: Tops | H60: 1 | I60: 450 | J60: Vodafone Cash | K60: Shipped | L60: 2026-07 | M60: =IF(AND(ISNUMBER(H60),ISNUMBER(I60)),H60*I60,"") -> 450
A61: 1091 | B61: 46201 | C61: أحمد رمضان | D61: 01019295578 | E61: Cairo | F61: T-Shirt | G61: Tops | H61: 1 | I61: 180 | J61: Instapay | K61: Delivered | L61: 2026-06 | M61: =IF(AND(ISNUMBER(H61),ISNUMBER(I61)),H61*I61,"") -> 180
A62: 1208 | B62: 46178 | C62: Mariam Hassan | D62: 01565723609 | F62: Jacket | G62: Outerwear | H62: 1 | I62: 1100 | J62: Cash On Delivery | K62: Delivered | L62: 2026-06 | M62: =IF(AND(ISNUMBER(H62),ISNUMBER(I62)),H62*I62,"") -> 1100
A63: 1232 | B63: 46226 | C63: Dina Hassan | D63: 01082735267 | E63: Alexandria | F63: Abaya | G63: Dresses | H63: 1 | I63: 900 | J63: Cash On Delivery | K63: Delivered | L63: 2026-07 | M63: =IF(AND(ISNUMBER(H63),ISNUMBER(I63)),H63*I63,"") -> 900
A64: 1311 | B64: 46200 | C64: كريم حسن | D64: 01164671344 | E64: Cairo | F64: Jeans | G64: Bottoms | H64: 3 | I64: 550 | J64: Cash On Delivery | K64: Cancelled | L64: 2026-06 | M64: =IF(AND(ISNUMBER(H64),ISNUMBER(I64)),H64*I64,"") -> 1650
A65: 1236 | B65: 46195 | C65: سارة محمود | D65: 01250090303 | E65: Cairo | F65: Skirt | G65: Bottoms | H65: 1 | I65: 300 | J65: Instapay | K65: Returned | L65: 2026-06 | M65: =IF(AND(ISNUMBER(H65),ISNUMBER(I65)),H65*I65,"") -> 300
A66: 1043 | B66: 46196 | C66: مصطفى سعد | D66: 01259828487 | E66: Cairo | F66: Abaya | G66: Dresses | H66: 2 | I66: 900 | J66: Cash On Delivery | K66: Delivered | L66: 2026-06 | M66: =IF(AND(ISNUMBER(H66),ISNUMBER(I66)),H66*I66,"") -> 1800
A67: 1279 | B67: 46184 | C67: سارة محمود | D67: Not provided | E67: Sohag | F67: Blouse | G67: Tops | H67: 1 | I67: 320 | J67: Cash On Delivery | K67: Delivered | L67: 2026-06 | M67: =IF(AND(ISNUMBER(H67),ISNUMBER(I67)),H67*I67,"") -> 320
A68: 1089 | B68: 46222 | C68: كريم السيد | D68: 01536656315 | E68: Alexandria | F68: Dress | G68: Dresses | H68: 1 | I68: 750 | J68: Vodafone Cash | K68: Shipped | L68: 2026-07 | M68: =IF(AND(ISNUMBER(H68),ISNUMBER(I68)),H68*I68,"") -> 750
A69: 1038 | B69: 46178 | C69: Dina Mahmoud | D69: 01288454746 | E69: Alexandria | F69: Blouse | G69: Tops | H69: 1 | I69: 320 | J69: Vodafone Cash | K69: Delivered | L69: 2026-06 | M69: =IF(AND(ISNUMBER(H69),ISNUMBER(I69)),H69*I69,"") -> 320
A70: 1240 | B70: 46222 | C70: سارة رمضان | D70: 01008896011 | E70: Cairo | F70: Scarf | G70: Accessories | H70: 2 | I70: 120 | J70: Instapay | K70: Delivered | L70: 2026-07 | M70: =IF(AND(ISNUMBER(H70),ISNUMBER(I70)),H70*I70,"") -> 240
A71: 1328 | B71: 46241 | C71: آية سعد | D71: 01209521719 | E71: Giza | F71: Dress | G71: Dresses | H71: 1 | I71: 750 | J71: Credit Card | K71: Delivered | L71: 2026-08 | M71: =IF(AND(ISNUMBER(H71),ISNUMBER(I71)),H71*I71,"") -> 750
A72: 1055 | B72: 46220 | C72: رنا عبدالله | D72: 01025533331 | E72: Giza | F72: Jacket | G72: Outerwear | H72: 1 | J72: Instapay | K72: Delivered | L72: 2026-07 | M72: =IF(AND(ISNUMBER(H72),ISNUMBER(I72)),H72*I72,"")
A73: 1407 | B73: 46241 | C73: كريم فتحي | D73: 01161638319 | E73: Giza | F73: T-Shirt | G73: Tops | H73: 1 | I73: 180 | J73: Cash On Delivery | K73: Shipped | L73: 2026-08 | M73: =IF(AND(ISNUMBER(H73),ISNUMBER(I73)),H73*I73,"") -> 180
A74: 1365 | B74: 46246 | C74: فاطمة السيد | D74: 01597737630 | E74: Alexandria | F74: T-Shirt | G74: Tops | H74: 1 | I74: 180 | J74: Vodafone Cash | K74: Delivered | L74: 2026-08 | M74: =IF(AND(ISNUMBER(H74),ISNUMBER(I74)),H74*I74,"") -> 180
A75: 1213 | B75: 46229 | C75: Karim Youssef | D75: 01082660733 | E75: Assiut | F75: Abaya | G75: Dresses | H75: 3 | I75: 900 | J75: Cash On Delivery | K75: Delivered | L75: 2026-07 | M75: =IF(AND(ISNUMBER(H75),ISNUMBER(I75)),H75*I75,"") -> 2700
A76: 1355 | B76: 46175 | C76: مريم عادل | D76: 01137405291 | E76: Giza | F76: Jeans | G76: Bottoms | H76: 1 | I76: 550 | J76: Cash On Delivery | K76: Shipped | L76: 2026-06 | M76: =IF(AND(ISNUMBER(H76),ISNUMBER(I76)),H76*I76,"") -> 550
A77: 1173 | B77: 46183 | C77: سارة يوسف | D77: 01026629380 | E77: Cairo | F77: Scarf | G77: Accessories | H77: 1 | I77: 120 | J77: Credit Card | K77: Shipped | L77: 2026-06 | M77: =IF(AND(ISNUMBER(H77),ISNUMBER(I77)),H77*I77,"") -> 120
A78: 1327 | B78: 46234 | C78: سارة عادل | D78: 01019107278 | E78: Alexandria | F78: T-Shirt | G78: Tops | H78: 1 | I78: 180 | J78: Credit Card | K78: Delivered | L78: 2026-07 | M78: =IF(AND(ISNUMBER(H78),ISNUMBER(I78)),H78*I78,"") -> 180
A79: 1439 | B79: 46235 | C79: سارة يوسف | D79: 01277382686 | E79: Alexandria | F79: Abaya | G79: Dresses | H79: 2 | I79: 900 | J79: Vodafone Cash | K79: Delivered | L79: 2026-08 | M79: =IF(AND(ISNUMBER(H79),ISNUMBER(I79)),H79*I79,"") -> 1800
A80: 1085 | B80: 46239 | C80: كريم خليل | D80: 01561132227 | E80: Alexandria | F80: Dress | G80: Dresses | H80: 2 | I80: 750 | J80: Cash On Delivery | K80: Delivered | L80: 2026-08 | M80: =IF(AND(ISNUMBER(H80),ISNUMBER(I80)),H80*I80,"") -> 1500
A81: 1420 | B81: 46243 | C81: Omar Mahmoud | D81: 01512597087 | E81: Sohag | F81: Skirt | G81: Bottoms | H81: 1 | I81: 300 | J81: Vodafone Cash | K81: Shipped | L81: 2026-08 | M81: =IF(AND(ISNUMBER(H81),ISNUMBER(I81)),H81*I81,"") -> 300
A82: 1263 | B82: 46227 | C82: علي محمود | D82: Not provided | E82: Mansoura | F82: Scarf | G82: Accessories | H82: 3 | I82: 120 | J82: Cash On Delivery | K82: Cancelled | L82: 2026-07 | M82: =IF(AND(ISNUMBER(H82),ISNUMBER(I82)),H82*I82,"") -> 360
A83: 1136 | B83: 46252 | C83: ياسمين صلاح | D83: 01091729180 | E83: Alexandria | F83: T-Shirt | G83: Tops | H83: 3 | I83: 180 | J83: Credit Card | K83: Delivered | L83: 2026-08 | M83: =IF(AND(ISNUMBER(H83),ISNUMBER(I83)),H83*I83,"") -> 540
A84: 1278 | B84: 46183 | C84: ندى خليل | D84: 01194338857 | E84: Mansoura | F84: Dress | G84: Dresses | H84: 1 | I84: 750 | J84: Cash On Delivery | K84: Cancelled | L84: 2026-06 | M84: =IF(AND(ISNUMBER(H84),ISNUMBER(I84)),H84*I84,"") -> 750
... A101: 1449 | B101: 46211 | C101: Nada Ibrahim | D101: 01592633989 | E101: Sohag | F101: Scarf | G101: Accessories | H101: 3 | I101: 120 | J101: Credit Card | K101: Cancelled | L101: 2026-07 | M101: =IF(AND(ISNUMBER(H101),ISNUMBER(I101)),H101*I101,"") -> 360
A102: 1238 | B102: 46195 | C102: عمر فتحي | D102: 01261187367 | E102: Giza | F102: Jacket | G102: Outerwear | H102: 1 | J102: Credit Card | K102: Delivered | L102: 2026-06 | M102: =IF(AND(ISNUMBER(H102),ISNUMBER(I102)),H102*I102,"")
A103: 1345 | B103: 46239 | C103: Nour Mahmoud | D103: 01244336742 | E103: Cairo | F103: Scarf | G103: Accessories | H103: 1 | I103: 120 | J103: Cash On Delivery | K103: Delivered | L103: 2026-08 | M103: =IF(AND(ISNUMBER(H103),ISNUMBER(I103)),H103*I103,"") -> 120
A104: 1075 | B104: 46239 | C104: Nour Ibrahim | D104: 01221410984 | E104: Mansoura | F104: Blouse | G104: Tops | H104: 2 | I104: 320 | J104: Credit Card | K104: Returned | L104: 2026-08 | M104: =IF(AND(ISNUMBER(H104),ISNUMBER(I104)),H104*I104,"") -> 640
A105: 1385 | B105: 46246 | C105: نور يوسف | D105: 01141940601 | E105: Cairo | F105: Jeans | G105: Bottoms | H105: 2 | I105: 550 | J105: Cash On Delivery | K105: Delivered | L105: 2026-08 | M105: =IF(AND(ISNUMBER(H105),ISNUMBER(I105)),H105*I105,"") -> 1100
A106: 1154 | B106: 46176 | C106: Dina Hassan | D106: 01117736765 | F106: T-Shirt | G106: Tops | H106: 1 | I106: 180 | J106: Cash On Delivery | K106: Delivered | L106: 2026-06 | M106: =IF(AND(ISNUMBER(H106),ISNUMBER(I106)),H106*I106,"") -> 180
A107: 1192 | B107: 46237 | C107: دينا خليل | D107: Not provided | E107: Tanta | F107: Abaya | G107: Dresses | H107: 2 | I107: 900 | J107: Instapay | K107: Delivered | L107: 2026-08 | M107: =IF(AND(ISNUMBER(H107),ISNUMBER(I107)),H107*I107,"") -> 1800
A108: 1300 | B108: 46226 | C108: دينا السيد | D108: 01022693640 | E108: Alexandria | F108: Jeans | G108: Bottoms | H108: 1 | I108: 550 | J108: Credit Card | K108: Cancelled | L108: 2026-07 | M108: =IF(AND(ISNUMBER(H108),ISNUMBER(I108)),H108*I108,"") -> 550
A109: 1261 | B109: 46229 | C109: Sara Hassan | D109: 01513413230 | E109: Cairo | F109: Scarf | G109: Accessories | H109: 1 | I109: 120 | J109: Cash On Delivery | K109: Shipped | L109: 2026-07 | M109: =IF(AND(ISNUMBER(H109),ISNUMBER(I109)),H109*I109,"") -> 120
A110: 1390 | B110: 46220 | C110: يوسف سعد | D110: 01294331925 | E110: Alexandria | F110: Jeans | G110: Bottoms | H110: 1 | I110: 550 | J110: Vodafone Cash | K110: Delivered | L110: 2026-07 | M110: =IF(AND(ISNUMBER(H110),ISNUMBER(I110)),H110*I110,"") -> 550
A111: 1382 | B111: 46248 | C111: إسراء صلاح | D111: 01072618604 | E111: Alexandria | F111: Jacket | G111: Outerwear | H111: 1 | I111: 1100 | J111: Vodafone Cash | K111: Cancelled | L111: 2026-08 | M111: =IF(AND(ISNUMBER(H111),ISNUMBER(I111)),H111*I111,"") -> 1100
A112: 1141 | B112: 46234 | C112: Ahmed Mahmoud | D112: 01597598661 | E112: Sohag | F112: Scarf | G112: Accessories | H112: 3 | J112: Cash On Delivery | K112: Delivered | L112: 2026-07 | M112: =IF(AND(ISNUMBER(H112),ISNUMBER(I112)),H112*I112,"")
A113: 1248 | B113: 46223 | C113: إسراء رمضان | D113: 01154273359 | E113: Sohag | F113: Dress | G113: Dresses | H113: 2 | I113: 750 | J113: Credit Card | K113: Shipped | L113: 2026-07 | M113: =IF(AND(ISNUMBER(H113),ISNUMBER(I113)),H113*I113,"") -> 1500
A114: 1084 | B114: 46216 | C114: إسراء رمضان | D114: 01581528376 | E114: Mansoura | F114: T-Shirt | G114: Tops | H114: 2 | I114: 180 | J114: Credit Card | K114: Shipped | L114: 2026-07 | M114: =IF(AND(ISNUMBER(H114),ISNUMBER(I114)),H114*I114,"") -> 360
A115: 1080 | B115: 46234 | C115: محمد رمضان | D115: 01075594394 | E115: Sohag | F115: Sneakers | G115: Shoes | H115: 2 | I115: 950 | J115: Vodafone Cash | K115: Returned | L115: 2026-07 | M115: =IF(AND(ISNUMBER(H115),ISNUMBER(I115)),H115*I115,"") -> 1900
A116: 1138 | B116: 46244 | C116: محمد فتحي | D116: 01039874664 | E116: Giza | F116: Blouse | G116: Tops | H116: 2 | I116: 320 | J116: Vodafone Cash | K116: Delivered | L116: 2026-08 | M116: =IF(AND(ISNUMBER(H116),ISNUMBER(I116)),H116*I116,"") -> 640
A117: 1347 | B117: 46211 | C117: هدى السيد | D117: 01079000213 | E117: Cairo | F117: Abaya | G117: Dresses | H117: 3 | I117: 900 | J117: Vodafone Cash | K117: Delivered | L117: 2026-07 | M117: =IF(AND(ISNUMBER(H117),ISNUMBER(I117)),H117*I117,"") -> 2700
A118: 1290 | B118: 46229 | C118: حسن رمضان | D118: Not provided | E118: Cairo | F118: Sneakers | G118: Shoes | H118: 2 | I118: 950 | J118: Vodafone Cash | K118: Cancelled | L118: 2026-07 | M118: =IF(AND(ISNUMBER(H118),ISNUMBER(I118)),H118*I118,"") -> 1900
A119: 1132 | B119: 46250 | C119: ندى رمضان | D119: 01209579916 | E119: Giza | F119: Blouse | G119: Tops | H119: 1 | I119: 320 | J119: Cash On Delivery | K119: Shipped | L119: 2026-08 | M119: =IF(AND(ISNUMBER(H119),ISNUMBER(I119)),H119*I119,"") -> 320
A120: 1239 | B120: 46249 | C120: يوسف محمود | D120: 01553616778 | E120: Giza | F120: Jeans | G120: Bottoms | H120: 2 | I120: 550 | J120: Credit Card | K120: Returned | L120: 2026-08 | M120: =IF(AND(ISNUMBER(H120),ISNUMBER(I120)),H120*I120,"") -> 1100
A121: 1131 | B121: 46244 | C121: Hoda Saad | D121: 01021185687 | E121: Alexandria | F121: Skirt | G121: Bottoms | H121: 1 | I121: 300 | J121: Credit Card | K121: Delivered | L121: 2026-08 | M121: =IF(AND(ISNUMBER(H121),ISNUMBER(I121)),H121*I121,"") -> 300
A122: 1268 | B122: 46176 | C122: ندى إبراهيم | D122: 01185356746 | E122: Sohag | F122: Skirt | G122: Bottoms | H122: 1 | I122: 300 | J122: Instapay | K122: Delivered | L122: 2026-06 | M122: =IF(AND(ISNUMBER(H122),ISNUMBER(I122)),H122*I122,"") -> 300
A123: 1315 | B123: 46245 | C123: منى إبراهيم | D123: Not provided | E123: Giza | F123: Skirt | G123: Bottoms | H123: 1 | I123: 300 | J123: Instapay | K123: Delivered | L123: 2026-08 | M123: =IF(AND(ISNUMBER(H123),ISNUMBER(I123)),H123*I123,"") -> 300
A124: 1229 | B124: 46234 | C124: مريم عبدالله | D124: 01234220595 | E124: Assiut | F124: Sneakers | G124: Shoes | H124: 1 | I124: 950 | J124: Vodafone Cash | K124: Delivered | L124: 2026-07 | M124: =IF(AND(ISNUMBER(H124),ISNUMBER(I124)),H124*I124,"") -> 950
... A134: 1191 | B134: 46261 | C134: ندى إبراهيم | D134: 01141782226 | E134: Mansoura | F134: Blouse | G134: Tops | H134: 3 | I134: 320 | J134: Cash On Delivery | K134: Cancelled | L134: 2026-08 | M134: =IF(AND(ISNUMBER(H134),ISNUMBER(I134)),H134*I134,"") -> 960
A135: 1259 | B135: 46243 | C135: رنا سعد | D135: 01576217694 | F135: Scarf | G135: Accessories | H135: 1 | I135: 120 | J135: Cash On Delivery | K135: Delivered | L135: 2026-08 | M135: =IF(AND(ISNUMBER(H135),ISNUMBER(I135)),H135*I135,"") -> 120
A136: 1331 | B136: 46250 | C136: Ahmed Youssef | D136: 01598282150 | E136: Tanta | F136: T-Shirt | G136: Tops | H136: 1 | I136: 180 | J136: Cash On Delivery | K136: Cancelled | L136: 2026-08 | M136: =IF(AND(ISNUMBER(H136),ISNUMBER(I136)),H136*I136,"") -> 180
A137: 1123 | B137: 46208 | C137: Fatma Ibrahim | D137: 01275043453 | E137: Cairo | F137: Abaya | G137: Dresses | H137: 2 | I137: 900 | J137: Cash On Delivery | K137: Delivered | L137: 2026-07 | M137: =IF(AND(ISNUMBER(H137),ISNUMBER(I137)),H137*I137,"") -> 1800
A138: 1092 | B138: 46228 | C138: رنا عبدالله | D138: 01099673413 | E138: Alexandria | F138: Blouse | G138: Tops | H138: 2 | I138: 320 | J138: Vodafone Cash | K138: Delivered | L138: 2026-07 | M138: =IF(AND(ISNUMBER(H138),ISNUMBER(I138)),H138*I138,"") -> 640
A139: 1158 | B139: 46208 | C139: هدى صلاح | D139: 01576716091 | E139: Cairo | F139: Dress | G139: Dresses | H139: 4 | I139: 750 | J139: Instapay | K139: Delivered | L139: 2026-07 | M139: =IF(AND(ISNUMBER(H139),ISNUMBER(I139)),H139*I139,"") -> 3000
A140: 1171 | B140: 46231 | C140: Hoda Saad | D140: 01281591950 | E140: Assiut | F140: Sneakers | G140: Shoes | H140: 2 | I140: 950 | J140: Vodafone Cash | K140: Shipped | L140: 2026-07 | M140: =IF(AND(ISNUMBER(H140),ISNUMBER(I140)),H140*I140,"") -> 1900
A141: 1122 | B141: 46252 | C141: Aya Saad | D141: 01266101043 | E141: Giza | F141: T-Shirt | G141: Tops | H141: 1 | I141: 180 | J141: Vodafone Cash | K141: Delivered | L141: 2026-08 | M141: =IF(AND(ISNUMBER(H141),ISNUMBER(I141)),H141*I141,"") -> 180
A142: 1436 | B142: 46225 | C142: آية سعد | D142: 01030484333 | E142: Mansoura | F142: Jacket | G142: Outerwear | H142: 1 | I142: 1100 | J142: Instapay | K142: Returned | L142: 2026-07 | M142: =IF(AND(ISNUMBER(H142),ISNUMBER(I142)),H142*I142,"") -> 1100
A143: 1244 | B143: 46235 | C143: رنا يوسف | D143: 01017997408 | E143: Cairo | F143: Abaya | G143: Dresses | H143: 1 | I143: 900 | J143: Cash On Delivery | K143: Cancelled | L143: 2026-08 | M143: =IF(AND(ISNUMBER(H143),ISNUMBER(I143)),H143*I143,"") -> 900
...

Sheet Cleaning Notes
A1: Cleaning Notes
A2: What was wrong with the raw file, what was done, and every assumption made.
A4: Row counts (from the raw-file audit)
A5: Item | B5: Rows | C5: Note
A6: Rows in raw file | B6: 486 | C6: Value from the raw Excel file
A7: Exact duplicate rows found | B7: 36 | C7: Duplicates are removed AFTER formatting is standardized
A8: Rows after cleaning | B8: =COUNTA('Cleaned Data'!$A$2:$A$451) -> 450 | C8: Live count from the 'Cleaned Data' sheet
A10: Missing values left after cleaning
A11: Column | B11: Blank cells | C11: Decision
A12: City | B12: =COUNTBLANK('Cleaned Data'!$E$2:$E$451) -> 20 | C12: Left blank. Unmapped values and the '-' placeholder are not guessed. These orders are excluded from the city table only.
A13: Qty | B13: =COUNTBLANK('Cleaned Data'!$H$2:$H$451) -> 5 | C13: Left blank. A guessed quantity would silently change totals.
A14: Price | B14: =COUNTBLANK('Cleaned Data'!$I$2:$I$451) -> 22 | C14: Left blank. Orders without a price have no revenue and are skipped by the revenue formulas.
A15: Orders without revenue | B15: =COUNTIF('Cleaned Data'!$M$2:$M$451,"") -> 25 | C15: Revenue totals are therefore slightly understated, not wrong.
A17: Issues found and how each was handled
A18: Column | C18: What was done
A19: Order Date | C19: Mixed formats (ISO, D/M/Y, D-Mon-Y, dotted, real dates) all converted to one date type. Dotted dates can be read two ways; the reading that falls inside the file's date range was used. Ambiguous cases default to day-first.
A20: City | C20: Arabic/English spellings, casing and abbreviations mapped to one English name per city.
A21: Price | C21: Text such as 'EGP 950', '950 جنيه' and '1,100' converted to numbers.
A22: Phone | C22: Unified to the 11-digit local format; '+20' removed; lost leading zeros restored.
A23: Product / Payment / Status | C23: Casing and spelling unified (e.g. Tshirt -> T-Shirt, COD -> Cash On Delivery).
A24: Qty | C24: The word 'two' converted to 2; placeholders left blank.
A25: Customer Name / Phone blanks | C25: Filled with a readable placeholder ('Not Found' / 'Not provided') because they are never used in a calculation.
A27: Data note: this practice project uses a simulated dataset that mimics a real messy export, so the business figures are illustrative.
